[
  { "id": 1, "nombre": "Ana", "edad": 25, "ciudad": "Santiago", "pais": "Chile", "area": "Ventas", "salario": 1200 },
  { "id": 2, "nombre": "Luis", "edad": 35, "ciudad": "Valparaiso", "pais": "Chile", "area": "Finanzas", "salario": 1850 },
  { "id": 3, "nombre": "Carla", "edad": 32, "ciudad": "Santiago", "pais": "Chile", "area": "Tecnologia", "salario": 2100 },
  { "id": 4, "nombre": "Pedro", "edad": 28, "ciudad": "Concepcion", "pais": "Chile", "area": "Operaciones", "salario": 1450 },
  { "id": 5, "nombre": "Marta", "edad": 41, "ciudad": "La Serena", "pais": "Chile", "area": "Recursos Humanos", "salario": 1750 },
  { "id": 6, "nombre": "Diego", "edad": 29, "ciudad": "Antofagasta", "pais": "Chile", "area": "Ventas", "salario": 1320 },
  { "id": 7, "nombre": "Camila", "edad": 27, "ciudad": "Temuco", "pais": "Chile", "area": "Marketing", "salario": 1280 },
  { "id": 8, "nombre": "Jorge", "edad": 38, "ciudad": "Santiago", "pais": "Chile", "area": "Tecnologia", "salario": 2400 },
  { "id": 9, "nombre": "Paula", "edad": 31, "ciudad": "Iquique", "pais": "Chile", "area": "Finanzas", "salario": 1680 },
  { "id": 10, "nombre": "Rosa", "edad": 26, "ciudad": "Puerto Montt", "pais": "Chile", "area": "Operaciones", "salario": 1380 },
  { "id": 11, "nombre": "Miguel", "edad": 34, "ciudad": "Lima", "pais": "Peru", "area": "Ventas", "salario": 1500 },
  { "id": 12, "nombre": "Lucia", "edad": 30, "ciudad": "Arequipa", "pais": "Peru", "area": "Marketing", "salario": 1420 },
  { "id": 13, "nombre": "Fernando", "edad": 45, "ciudad": "Lima", "pais": "Peru", "area": "Direccion", "salario": 2800 },
  { "id": 14, "nombre": "Daniela", "edad": 33, "ciudad": "Cusco", "pais": "Peru", "area": "Recursos Humanos", "salario": 1600 },
  { "id": 15, "nombre": "Oscar", "edad": 29, "ciudad": "Trujillo", "pais": "Peru", "area": "Tecnologia", "salario": 1950 },
  { "id": 16, "nombre": "Valeria", "edad": 37, "ciudad": "Lima", "pais": "Peru", "area": "Finanzas", "salario": 2050 },
  { "id": 17, "nombre": "Sofia", "edad": 24, "ciudad": "Buenos Aires", "pais": "Argentina", "area": "Ventas", "salario": 1180 },
  { "id": 18, "nombre": "Tomas", "edad": 39, "ciudad": "Cordoba", "pais": "Argentina", "area": "Operaciones", "salario": 1720 },
  { "id": 19, "nombre": "Julieta", "edad": 28, "ciudad": "Rosario", "pais": "Argentina", "area": "Marketing", "salario": 1360 },
  { "id": 20, "nombre": "Andres", "edad": 36, "ciudad": "Buenos Aires", "pais": "Argentina", "area": "Tecnologia", "salario": 2250 },
  { "id": 21, "nombre": "Florencia", "edad": 31, "ciudad": "Mendoza", "pais": "Argentina", "area": "Finanzas", "salario": 1660 },
  { "id": 22, "nombre": "Nicolas", "edad": 27, "ciudad": "Cordoba", "pais": "Argentina", "area": "Ventas", "salario": 1250 },
  { "id": 23, "nombre": "Laura", "edad": 42, "ciudad": "Bogota", "pais": "Colombia", "area": "Direccion", "salario": 2900 },
  { "id": 24, "nombre": "Juan", "edad": 29, "ciudad": "Medellin", "pais": "Colombia", "area": "Tecnologia", "salario": 2080 },
  { "id": 25, "nombre": "Sara", "edad": 26, "ciudad": "Cali", "pais": "Colombia", "area": "Marketing", "salario": 1300 },
  { "id": 26, "nombre": "Felipe", "edad": 35, "ciudad": "Bogota", "pais": "Colombia", "area": "Finanzas", "salario": 1980 },
  { "id": 27, "nombre": "Natalia", "edad": 32, "ciudad": "Cartagena", "pais": "Colombia", "area": "Recursos Humanos", "salario": 1580 },
  { "id": 28, "nombre": "Ricardo", "edad": 40, "ciudad": "Medellin", "pais": "Colombia", "area": "Operaciones", "salario": 1820 },
  { "id": 29, "nombre": "Elena", "edad": 33, "ciudad": "Ciudad de Mexico", "pais": "Mexico", "area": "Ventas", "salario": 1700 },
  { "id": 30, "nombre": "Pablo", "edad": 28, "ciudad": "Guadalajara", "pais": "Mexico", "area": "Tecnologia", "salario": 2150 },
  { "id": 31, "nombre": "Mariana", "edad": 30, "ciudad": "Monterrey", "pais": "Mexico", "area": "Marketing", "salario": 1490 },
  { "id": 32, "nombre": "Hector", "edad": 44, "ciudad": "Ciudad de Mexico", "pais": "Mexico", "area": "Direccion", "salario": 3000 },
  { "id": 33, "nombre": "Adriana", "edad": 27, "ciudad": "Puebla", "pais": "Mexico", "area": "Finanzas", "salario": 1540 },
  { "id": 34, "nombre": "Gabriel", "edad": 38, "ciudad": "Merida", "pais": "Mexico", "area": "Operaciones", "salario": 1760 },
  { "id": 35, "nombre": "Teresa", "edad": 29, "ciudad": "Quito", "pais": "Ecuador", "area": "Ventas", "salario": 1410 },
  { "id": 36, "nombre": "Martin", "edad": 34, "ciudad": "Guayaquil", "pais": "Ecuador", "area": "Tecnologia", "salario": 2020 },
  { "id": 37, "nombre": "Isabel", "edad": 31, "ciudad": "Quito", "pais": "Ecuador", "area": "Recursos Humanos", "salario": 1570 },
  { "id": 38, "nombre": "Alvaro", "edad": 43, "ciudad": "Cuenca", "pais": "Ecuador", "area": "Finanzas", "salario": 1880 },
  { "id": 39, "nombre": "Cecilia", "edad": 26, "ciudad": "Guayaquil", "pais": "Ecuador", "area": "Marketing", "salario": 1350 },
  { "id": 40, "nombre": "Bruno", "edad": 37, "ciudad": "Quito", "pais": "Ecuador", "area": "Operaciones", "salario": 1730 }
]
